dfk/__init__.py
dfk/cli.py
dfk/config.py
dfk/commands/__init__.py
dfk/commands/cmd_campaign.py
dfk/commands/cmd_ijk.py
dfk/commands/cmd_login.py
dfk/commands/cmd_plan.py
dfk/commands/cmd_slave.py
dfk/commands/cmd_sysconfig.py
dfk-0.1.3.dist-info/METADATA
dfk-0.1.3.dist-info/WHEEL
dfk-0.1.3.dist-info/entry_points.txt
dfk-0.1.3.dist-info/top_level.txt
dfk-0.1.3.dist-info/RECORD
