Metadata-Version: 2.1
Name: dfk
Version: 0.1.3
Summary: A command-line tool for defektor 👨‍💻
Home-page: https://github.com/SysOBs/dfk.git
Author: SysOBs
Author-email: sob@dei.uc.pt
License: UNKNOWN
Platform: UNKNOWN
Classifier: Programming Language :: Python :: 3
Classifier: Operating System :: OS Independent
Requires-Python: >=3.6
Requires-Dist: click (==7.1.1)
Requires-Dist: click-completion (==0.5.2)
Requires-Dist: defektor-api (==0.1.2)
Requires-Dist: python-jsonschema-objects (==0.3.12)
Requires-Dist: jsonschema (==3.2.0)
Requires-Dist: setuptools (~=46.1.3)
